setup.py
argon/__init__.py
argon/generatorpython.py
xenon1234.egg-info/PKG-INFO
xenon1234.egg-info/SOURCES.txt
xenon1234.egg-info/dependency_links.txt
xenon1234.egg-info/top_level.txt