Metadata-Version: 1.0
Name: xenon1234
Version: 0.1.0
Summary: Useful towel-related stuff.
Home-page: http://pypi.python.org/pypi/
Author: name surname
Author-email: name@addr.ess
License: UNKNOWN
Platform: UNKNOWN
